Workbook

Sheet fornecedores
A1: Período | B1: Fornecedor | C1: Último pagto ano | D1: CPF/CNPJ | E1: Valor Pago | F1: MÊS
A2: 2026 | B2: A. C. R. AVALIACOES LTDA - ME | C2: 46083 | D2: 08.890.317/0001-52 | E2: 3920 | F2: =TEXT(MONTH(C2)*29,"mmmm") -> março
A3: 2026 | B3: ABBOTT LABORATORIOS DO BRASIL LTDA | C3: 46080 | D3: 56.998.701/0033-01 | E3: 266800 | F3: =TEXT(MONTH(C3)*29,"mmmm") -> fevereiro
A4: 2026 | B4: ABC TRANSPORTES COLETIVOS VALE PARAIBA LTDA | C4: 46076 | D4: 45.176.864/0001-05 | E4: 1118.6 | F4: =TEXT(MONTH(C4)*29,"mmmm") -> fevereiro
A5: 2026 | B5: ABIGAIR ANDRADE DO CARMO | C5: 46059 | D5: 515.520.518-20 | E5: 22 | F5: =TEXT(MONTH(C5)*29,"mmmm") -> fevereiro
A6: 2026 | B6: ABR ACESSORIOS LTDA. | C6: 46045 | D6: 52.301.374/0001-40 | E6: 17990 | F6: =TEXT(MONTH(C6)*29,"mmmm") -> janeiro
A7: 2026 | B7: ABRAAO MARTINS ROMERO | C7: 46048 | D7: 535.999.128-31 | E7: 44 | F7: =TEXT(MONTH(C7)*29,"mmmm") -> janeiro
A8: 2026 | B8: ACACIA COMERCIO DE MEDICAMENTOS LTDA | C8: 46086 | D8: 03.945.035/0001-91 | E8: 60150.79 | F8: =TEXT(MONTH(C8)*29,"mmmm") -> março
A9: 2026 | B9: ACACIO ALEXANDRE DOS SANTOS | C9: 46045 | D9: 371.601.778-78 | E9: 3000 | F9: =TEXT(MONTH(C9)*29,"mmmm") -> janeiro
A10: 2026 | B10: ACAF- ASSOC. DOS CLUBES AMADORES DE FUT. SJC | C10: 46086 | D10: 04.533.920/0001-26 | E10: 109859.91 | F10: =TEXT(MONTH(C10)*29,"mmmm") -> março
A11: 2026 | B11: ACAPU COMERCIO DE MADEIRAS LTDA | C11: 46028 | D11: 14.139.819/0001-49 | E11: 58082.77 | F11: =TEXT(MONTH(C11)*29,"mmmm") -> janeiro
A12: 2026 | B12: ACQUA BRILHO LAVANDERIA LTDA | C12: 46076 | D12: 36.774.430/0001-08 | E12: 524 | F12: =TEXT(MONTH(C12)*29,"mmmm") -> fevereiro
A13: 2026 | B13: ACTA MEDICINA DIAGNOSTICA LTDA | C13: 46072 | D13: 04.109.493/0001-53 | E13: 516623.5 | F13: =TEXT(MONTH(C13)*29,"mmmm") -> fevereiro
... A4591: 2026 | B4591: 62.213.408 CARLOS EDUARDO RIBEIRO DOS SANTOS | C4591: 46042 | D4591: 62.213.408/0001-07 | E4591: 5600 | F4591: =TEXT(MONTH(C4591)*29,"mmmm") -> janeiro

Sheet Planilha1
A1: Mês | B1: Total ultimo pagamento | C1: total de itens
A2: janeiro | B2: =SUMIF(fornecedores!$F$2:$F$4591,Planilha1!A2,fornecedores!$E$2:$E$4591) -> 8500790 | C2: =COUNTIF(fornecedores!F2:F4591,Planilha1!A2) -> 926
A3: fevereiro | B3: =SUMIF(fornecedores!$F$2:$F$4591,Planilha1!A3,fornecedores!$E$2:$E$4591) -> 1.7460159e+08 | C3: =COUNTIF(fornecedores!F3:F4592,Planilha1!A3) -> 2632
A4: março | B4: =SUMIF(fornecedores!$F$2:$F$4591,Planilha1!A4,fornecedores!$E$2:$E$4591) -> 4.3588095e+08 | C4: =COUNTIF(fornecedores!F4:F4593,Planilha1!A4) -> 1031
A5: abril | B5: =SUMIF(fornecedores!$F$2:$F$4591,Planilha1!A5,fornecedores!$E$2:$E$4591) -> 0 | C5: =COUNTIF(fornecedores!F5:F4594,Planilha1!A5) -> 0
A6: maio | B6: =SUMIF(fornecedores!$F$2:$F$4591,Planilha1!A6,fornecedores!$E$2:$E$4591) -> 0 | C6: =COUNTIF(fornecedores!F6:F4595,Planilha1!A6) -> 0
A7: junho | B7: =SUMIF(fornecedores!$F$2:$F$4591,Planilha1!A7,fornecedores!$E$2:$E$4591) -> 0 | C7: =COUNTIF(fornecedores!F7:F4596,Planilha1!A7) -> 0
A8: julho | B8: =SUMIF(fornecedores!$F$2:$F$4591,Planilha1!A8,fornecedores!$E$2:$E$4591) -> 0 | C8: =COUNTIF(fornecedores!F8:F4597,Planilha1!A8) -> 0
A9: agosto | B9: =SUMIF(fornecedores!$F$2:$F$4591,Planilha1!A9,fornecedores!$E$2:$E$4591) -> 0 | C9: =COUNTIF(fornecedores!F9:F4598,Planilha1!A9) -> 0
A10: setembro | B10: =SUMIF(fornecedores!$F$2:$F$4591,Planilha1!A10,fornecedores!$E$2:$E$4591) -> 0 | C10: =COUNTIF(fornecedores!F10:F4599,Planilha1!A10) -> 0
A11: outubro | B11: =SUMIF(fornecedores!$F$2:$F$4591,Planilha1!A11,fornecedores!$E$2:$E$4591) -> 0 | C11: =COUNTIF(fornecedores!F11:F4600,Planilha1!A11) -> 0
A12: novembro | B12: =SUMIF(fornecedores!$F$2:$F$4591,Planilha1!A12,fornecedores!$E$2:$E$4591) -> 0 | C12: =COUNTIF(fornecedores!F12:F4601,Planilha1!A12) -> 0
A13: dezembro | B13: =SUMIF(fornecedores!$F$2:$F$4591,Planilha1!A13,fornecedores!$E$2:$E$4591) -> 0 | C13: =COUNTIF(fornecedores!F13:F4602,Planilha1!A13) -> 0
